{
  "main": {
    "id": "5324373015726ba8",
    "type": "split",
    "children": [
      {
        "id": "4509724f8bf84da7",
        "type": "tabs",
        "children": [
          {
            "id": "ad71d89f9e5e7e4e",
            "type": "leaf",
            "pinned": true,
            "state": {
              "type": "markdown",
              "state": {
                "file": "Base/Модуль_2.md",
                "mode": "source",
                "source": false
              },
              "pinned": true,
              "icon": "lucide-file",
              "title": "Модуль_2"
            }
          },
          {
            "id": "5d9b48b337d5eb64",
            "type": "leaf",
            "state": {
              "type": "markdown",
              "state": {
                "file": "Base/Властивості свідомості.md",
                "mode": "source",
                "source": false
              },
              "icon": "lucide-file",
              "title": "Властивості свідомості"
            }
          }
        ],
        "currentTab": 1
      }
    ],
    "direction": "vertical"
  },
  "left": {
    "id": "23164d01c43d26f9",
    "type": "split",
    "children": [
      {
        "id": "25270321051ffc6e",
        "type": "tabs",
        "children": [
          {
            "id": "a0fa698eb179cdf9",
            "type": "leaf",
            "state": {
              "type": "file-explorer",
              "state": {
                "sortOrder": "alphabetical"
              },
              "icon": "lucide-folder-closed",
              "title": "Files"
            }
          },
          {
            "id": "2b84374726366f43",
            "type": "leaf",
            "state": {
              "type": "markdown",
              "state": {
                "file": "Templates/template.md",
                "mode": "source",
                "source": false
              },
              "icon": "lucide-file",
              "title": "template"
            }
          },
          {
            "id": "c0538b93adac7463",
            "type": "leaf",
            "state": {
              "type": "search",
              "state": {
                "query": "tag:#розлад_мислення",
                "matchingCase": false,
                "explainSearch": false,
                "collapseAll": false,
                "extraContext": false,
                "sortOrder": "alphabetical"
              },
              "icon": "lucide-search",
              "title": "Search"
            }
          },
          {
            "id": "86b049d3431ea9f0",
            "type": "leaf",
            "state": {
              "type": "bookmarks",
              "state": {},
              "icon": "lucide-bookmark",
              "title": "Bookmarks"
            }
          }
        ]
      }
    ],
    "direction": "horizontal",
    "width": 300
  },
  "right": {
    "id": "67afd9db2c354731",
    "type": "split",
    "children": [
      {
        "id": "cea99ba8918fdd49",
        "type": "tabs",
        "children": [
          {
            "id": "afbcd3c8066907ba",
            "type": "leaf",
            "state": {
              "type": "backlink",
              "state": {
                "file": "Base/books.md",
                "collapseAll": false,
                "extraContext": false,
                "sortOrder": "alphabetical",
                "showSearch": false,
                "searchQuery": "",
                "backlinkCollapsed": false,
                "unlinkedCollapsed": true
              },
              "icon": "links-coming-in",
              "title": "Backlinks for books"
            }
          }
        ]
      }
    ],
    "direction": "horizontal",
    "width": 300,
    "collapsed": true
  },
  "left-ribbon": {
    "hiddenItems": {
      "switcher:Open quick switcher": false,
      "canvas:Create new canvas": false,
      "command-palette:Open command palette": false,
      "graph:Open graph view": false,
      "markdown-importer:Open format converter": false,
      "templates:Insert template": false,
      "obsidian-git:Open Git source control": false,
      "homepage:Open homepage": false,
      "templater-obsidian:Templater": false,
      "obsidian-book-search-plugin:Create new book note": false
    }
  },
  "active": "5d9b48b337d5eb64",
  "lastOpenFiles": [
    "Base/Модуль_2.md",
    "Base/Пропедевтика_психіатрії.md",
    "Base/courses.md",
    "home/Homepage.md",
    "Base/Властивості свідомості.md",
    "Base/Складові свідомості.md",
    "Templates/template.md",
    "Base/Екзистенційна психотерапія.md",
    "Base/books.md",
    "Base/Психопатологічні синдроми.md",
    "Base/Модуль_1.md",
    "Base/Психоз-невроз.md",
    "Base/Симптоми.md",
    "Base/конспекти по книжці Екзистенційна психотерапія.md",
    "Templates/book template.md",
    "Base/Критерії психічного здоров'я.md",
    "Base/шизофренічне_мислення.md",
    "Base/Хворобливі ідеї.md",
    "Base/Синдроми рухових розладів.md",
    "Base/Розлади потягів.md",
    "Base/Порушення волі.md",
    "Base/мовні стереотипи.md",
    "Base/Маячні ідеї.md",
    "Base/Класифікація розладів мислення.md",
    "Base/Класифікаціія розладів волі.md",
    "Base/Класифікація розладів сприйняття.md",
    "Files/The Denial of Death.jpg",
    "/The Denial of Death.jpg",
    "Files/Pasted image 20241121015010.jpg",
    "Files/The Oxford Handbook of Clinical Psychology 1.jpg",
    "Files/The Oxford Handbook of Clinical Psychology.jpg",
    "Files/The Oxford Handbook of Clinical Psychology.jpg",
    "/The Oxford Handbook of Clinical Psychology.jpg",
    "projects/movies",
    "projects/youtube",
    "projects/articles",
    "projects/books",
    "projects/courses",
    "projects/work",
    "Untitled",
    "projects",
    "home",
    "Untitled.canvas",
    "Files/Pasted image 20240926220313.png",
    "Files/Pasted image 20240926215434.png",
    "Files/Pasted image 20240926215256.png",
    "Templates",
    "psychology.canvas"
  ]
}